eshgham/__init__.py
eshgham/__main__.py
eshgham/_installed_version.py
eshgham/version.py
eshgham/tests/__init__.py
eshgham/tests/test_color_outputter.py
eshgham/tests/test_getdata.py
eshgham/tests/test_json_outputter.py
eshgham/tests/test_main.py
eshgham/tests/test_models.py
eshgham-0.4.0.dist-info/licenses/LICENSE
eshgham-0.4.0.dist-info/METADATA
eshgham-0.4.0.dist-info/WHEEL
eshgham-0.4.0.dist-info/entry_points.txt
eshgham-0.4.0.dist-info/top_level.txt
eshgham-0.4.0.dist-info/RECORD
